Workbook

Sheet Dashboard
A1: MindPulse AI Research Foundation — Operations Dashboard
A3: Total Topics | B3: Active Topics | C3: Papers Analyzed | D3: Findings Curated | E3: Newsletter Subs | F3: Monthly Revenue | G3: Agent Uptime | H3: Avg Confidence
A4: =COUNTA('Research Topics'!A4:A103) -> 14 | B4: =COUNTIF('Research Topics'!F4:F103,"Active") -> 10 | C4: =COUNTA('Paper Analysis Log'!A4:A5003) -> 8 | D4: =SUM('Paper Analysis Log'!I4:I5003) -> 15 | E4: ='Newsletter & Social'!B5 -> 0.42 | F4: ='Budget & Revenue'!N6 -> 15000 | G4: ='Agent Performance'!B5 -> 168 | H4: =AVERAGE('Paper Analysis Log'!H4:H5003) -> 0.82625
A6: Research Focus Area Status
A7: Focus Area | B7: Status | C7: Papers This Month | D7: Key Finding This Week
A8: PTSD | B8: Active — Primary | C8: =COUNTIFS('Paper Analysis Log'!C4:C5003,"PTSD",'Paper Analysis Log'!B4:B5003,">="&DATE(YEAR(TODAY()),MONTH(TODAY()),1)) -> 0 | D8: Psilocybin 67% remission at 12mo
A9: Depression | B9: Active — Secondary | C9: =COUNTIFS('Paper Analysis Log'!C4:C5003,"Depression",'Paper Analysis Log'!B4:B5003,">="&DATE(YEAR(TODAY()),MONTH(TODAY()),1)) -> 0 | D9: Gut microbiome predicts SSRI response
A10: Anxiety | B10: Planned — Q3 2027 | C10: =COUNTIFS('Paper Analysis Log'!C4:C5003,"Anxiety",'Paper Analysis Log'!B4:B5003,">="&DATE(YEAR(TODAY()),MONTH(TODAY()),1)) -> 0 | D10: Digital CBT matches in-person therapy
A11: Cross-Condition | B11: Active — Ongoing | C11: =COUNTIFS('Paper Analysis Log'!C4:C5003,"Cross-Condition",'Paper Analysis Log'!B4:B5003,">="&DATE(YEAR(TODAY()),MONTH(TODAY()),1)) -> 0 | D11: IL-6 linked to comorbid phenotype

Sheet Research Topics
A1: Research Topics & Sub-Topics
A2: Track all research areas, priorities, data sources, and progress
A3: Topic ID | B3: Focus Area | C3: Sub-Topic | D3: Description | E3: Priority | F3: Status | G3: Data Sources | H3: Key Search Terms | I3: Papers Found | J3: Papers Analyzed | K3: Findings Generated | L3: Last Updated
A4: PTSD-001 | B4: PTSD | C4: Psychedelic-Assisted Therapy | D4: Psilocybin, MDMA, ketamine for PTSD treatment | E4: High | F4: Active | G4: PubMed, ClinicalTrials.gov, bioRxiv | H4: psilocybin PTSD, MDMA therapy, psychedelic trauma | I4: 342 | J4: 187 | K4: 56 | L4: 2026-03-29
A5: PTSD-002 | B5: PTSD | C5: EMDR Advances | D5: Eye Movement Desensitization and Reprocessing updates | E5: High | F5: Active | G5: PubMed, PsycINFO | H5: EMDR PTSD, eye movement desensitization, trauma processing | I5: 218 | J5: 134 | K5: 38 | L5: 2026-03-29
A6: PTSD-003 | B6: PTSD | C6: Veteran PTSD | D6: PTSD in military veterans, VA treatment outcomes | E6: High | F6: Active | G6: PubMed, VA Research, PTSD Repository | H6: veteran PTSD, military trauma, combat stress, VA outcomes | I6: 456 | J6: 289 | K6: 72 | L6: 2026-03-29
A7: PTSD-004 | B7: PTSD | C7: Digital Therapeutics for PTSD | D7: App-based and VR exposure therapy | E7: Medium | F7: Active | G7: PubMed, IEEE, ACM Digital Library | H7: VR exposure therapy, PTSD app, digital therapeutic trauma | I7: 124 | J7: 67 | K7: 19 | L7: 2026-03-28
A8: PTSD-005 | B8: PTSD | C8: PTSD Biomarkers | D8: Cortisol, inflammatory markers, neuroimaging for PTSD | E8: Medium | F8: Active | G8: PubMed, bioRxiv | H8: PTSD biomarker, cortisol trauma, HPA axis PTSD | I8: 287 | J8: 156 | K8: 41 | L8: 2026-03-29
A9: DEP-001 | B9: Depression | C9: Inflammation-Depression Link | D9: Neuroinflammation and cytokine role in MDD | E9: High | F9: Active | G9: PubMed, bioRxiv | H9: depression inflammation, IL-6 depression, neuroinflammation MDD | I9: 534 | J9: 312 | K9: 89 | L9: 2026-03-29
A10: DEP-002 | B10: Depression | C10: Gut-Brain Axis | D10: Microbiome influence on depression and treatment response | E10: High | F10: Active | G10: PubMed, Nature Reviews | H10: gut microbiome depression, microbiota-gut-brain, SSRI microbiome | I10: 198 | J10: 112 | K10: 34 | L10: 2026-03-29
A11: DEP-003 | B11: Depression | C11: Treatment-Resistant Depression | D11: Interventions for TRD including ketamine, TMS, DBS | E11: High | F11: Active | G11: PubMed, ClinicalTrials.gov | H11: treatment resistant depression, ketamine TRD, TMS depression | I11: 367 | J11: 201 | K11: 58 | L11: 2026-03-28
A12: DEP-004 | B12: Depression | C12: Depression Pharmacogenomics | D12: Genetic predictors of antidepressant response | E12: Medium | F12: Planned | G12: PubMed, PharmGKB | H12: pharmacogenomics depression, CYP450 antidepressant, genetic SSRI | I12: 145 | J12: 0 | K12: 0
A13: ANX-001 | B13: Anxiety | C13: Digital CBT Efficacy | D13: App-based CBT for generalized anxiety and social anxiety | E13: Medium | F13: Planned | G13: PubMed, PsycINFO | H13: digital CBT anxiety, app therapy GAD, mobile CBT | I13: 89 | J13: 0 | K13: 0
A14: ANX-002 | B14: Anxiety | C14: Anxiety-Gut Connection | D14: Microbiome influences on anxiety disorders | E14: Medium | F14: Planned | G14: PubMed, bioRxiv | H14: gut microbiome anxiety, probiotics anxiety, microbiota GAD | I14: 76 | J14: 0 | K14: 0
A15: CC-001 | B15: Cross-Condition | C15: Heart-Brain Axis | D15: Cardiovascular risk and mental health comorbidity | E15: Medium | F15: Active | G15: PubMed, Circulation, JAMA Cardiology | H15: depression cardiovascular, PTSD heart disease, anxiety cardiac | I15: 312 | J15: 178 | K15: 45 | L15: 2026-03-29
A16: CC-002 | B16: Cross-Condition | C16: Shared Biomarkers | D16: Common inflammatory and genetic markers across conditions | E16: High | F16: Active | G16: PubMed, bioRxiv | H16: IL-6 comorbid, shared biomarker depression anxiety, transdiagnostic marker | I16: 167 | J16: 98 | K16: 27 | L16: 2026-03-29
A17: TOTALS | I17: =SUM(I4:I16) -> 3315 | J17: =SUM(J4:J16) -> 1734 | K17: =SUM(K4:K16) -> 479

Sheet Paper Analysis Log
A1: Daily Paper Analysis Log
A2: Every paper analyzed by the AI agents is logged here with key metadata and findings
A3: Paper ID | B3: Date Analyzed | C3: Focus Area | D3: Sub-Topic | E3: Title | F3: Source Journal | G3: Study Type | H3: Confidence Score | I3: Findings Count | J3: Sample Size | K3: Key Finding Summary | L3: Contradicts Existing? | M3: Priority Flag
A4: PAP-2026-0329-001 | B4: 2026-03-29 | C4: PTSD | D4: Psychedelic-Assisted Therapy | E4: Psilocybin-Assisted Therapy for Treatment-Resistant PTSD: Phase 2b RCT | F4: Lancet Psychiatry | G4: RCT | H4: 0.92 | I4: 3 | J4: 218 | K4: 67% remission at 12-month follow-up; significantly outperformed prolonged exposure alone | L4: No | M4: High
A5: PAP-2026-0329-002 | B5: 2026-03-29 | C5: Depression | D5: Gut-Brain Axis | E5: Gut Microbiome Signature Predicts SSRI Response with 78% Accuracy | F5: Nature Medicine | G5: Meta-Analysis | H5: 0.85 | I5: 2 | J5: 1847 | K5: 12-species gut microbiome panel predicts SSRI treatment response; validated across 4 cohorts | L5: No | M5: High
A6: PAP-2026-0329-003 | B6: 2026-03-29 | C6: Anxiety | D6: Digital CBT Efficacy | E6: AI-Guided Smartphone CBT Non-Inferior to Face-to-Face for GAD | F6: JAMA Psychiatry | G6: RCT | H6: 0.88 | I6: 2 | J6: 3200 | K6: 52-week non-inferiority; 82% adherence vs 64% for in-person; equivalent symptom reduction | L6: No | M6: High
A7: PAP-2026-0329-004 | B7: 2026-03-29 | C7: Cross-Condition | D7: Shared Biomarkers | E7: IL-6 as Transdiagnostic Biomarker for Comorbid Depression-Anxiety | F7: Biological Psychiatry | G7: Systematic Review | H7: 0.74 | I7: 1 | J7: 0 | K7: Elevated IL-6 consistently appears in comorbid depression-anxiety phenotype across 7 studies | L7: Partially | M7: Medium
A8: PAP-2026-0329-005 | B8: 2026-03-29 | C8: PTSD | D8: Veteran PTSD | E8: Prolonged Exposure vs CPT in OEF/OIF Veterans: 5-Year Follow-Up | F8: Journal of Clinical Psychology | G8: Longitudinal | H8: 0.81 | I8: 2 | J8: 340 | K8: No significant difference at 5 years; both show 55% sustained improvement; dropout predicts relapse | L8: No | M8: Medium
A9: PAP-2026-0328-006 | B9: 2026-03-28 | C9: Depression | D9: Treatment-Resistant Depression | E9: Esketamine Nasal Spray Real-World Effectiveness in Community Settings | F9: American Journal of Psychiatry | G9: Observational | H9: 0.79 | I9: 2 | J9: 1200 | K9: Real-world effectiveness lower than clinical trial (41% vs 53% response); adherence key factor | L9: Partially | M9: Medium
A10: PAP-2026-0328-007 | B10: 2026-03-28 | C10: PTSD | D10: PTSD Biomarkers | E10: Machine Learning Classification of PTSD Using Resting-State fMRI | F10: NeuroImage: Clinical | G10: Cross-Sectional | H10: 0.72 | I10: 1 | J10: 156 | K10: ML model achieves 83% classification accuracy for PTSD using default mode network connectivity | L10: No | M10: Low
A11: PAP-2026-0328-008 | B11: 2026-03-28 | C11: Cross-Condition | D11: Heart-Brain Axis | E11: Depression as Independent Risk Factor for Heart Failure: Updated Meta-Analysis | F11: Circulation | G11: Meta-Analysis | H11: 0.9 | I11: 2 | J11: 892000 | K11: Depression increases HF risk by 1.6x (HR=1.58); dose-response relationship with severity | L11: No | M11: High

Sheet Agent Performance
A1: AI Agent Performance Dashboard
A3: Overall System Metrics
A4: System Uptime | B4: 0.987
A5: Avg Daily Papers Scanned | B5: 168
A6: Avg Daily Papers Analyzed | B6: 12
A7: Avg Processing Time (min) | B7: 4.2
A8: False Positive Rate | B8: 0.03
A9: Avg Confidence Score | B9: 0.83
A12: Agent Performance Breakdown
A13: Agent Name | B13: Status | C13: Tasks Today | D13: Tasks Completed | E13: Completion Rate | F13: Avg Time (min) | G13: Errors Today | H13: Error Rate
A14: CEO Orchestrator | B14: Active | C14: 45 | D14: 45 | E14: =D14/C14 -> 1 | F14: 0.5 | G14: 0 | H14: =G14/C14 -> 0
A15: Research Director | B15: Active | C15: 228 | D15: 225 | E15: =D15/C15 -> 0.98684211 | F15: 2.1 | G15: 3 | H15: =G15/C15 -> 0.013157895
A16: Data Analyst Alpha | B16: Active | C16: 5 | D16: 5 | E16: =D16/C16 -> 1 | F16: 18.3 | G16: 0 | H16: =G16/C16 -> 0
A17: Data Analyst Beta | B17: Active | C17: 4 | D17: 4 | E17: =D17/C17 -> 1 | F17: 22.1 | G17: 0 | H17: =G17/C17 -> 0
A18: Data Analyst Gamma | B18: Active | C18: 5 | D18: 4 | E18: =D18/C18 -> 0.8 | F18: 19.7 | G18: 1 | H18: =G18/C18 -> 0.2
A19: Pattern Detector | B19: Processing | C19: 1 | D19: 0 | E19: =IF(C19=0,0,D19/C19) -> 0 | F19: 0 | G19: 0 | H19: =IF(C19=0,0,G19/C19) -> 0
A20: Quality Controller | B20: Queued | C20: 0 | D20: 0 | E20: =IF(C20=0,0,D20/C20) -> 0 | F20: 0 | G20: 0 | H20: =IF(C20=0,0,G20/C20) -> 0
A21: Communications Agent | B21: Active | C21: 3 | D21: 3 | E21: =D21/C21 -> 1 | F21: 8.4 | G21: 0 | H21: =G21/C21 -> 0
A22: TOTALS | C22: =SUM(C14:C21) -> 291 | D22: =SUM(D14:D21) -> 286 | E22: =IF(C22=0,0,D22/C22) -> 0.98281787 | G22: =SUM(G14:G21) -> 4 | H22: =IF(C22=0,0,G22/C22) -> 0.013745704

Sheet Newsletter & Social
A1: Newsletter & Social Media Metrics
A3: Newsletter Metrics
A4: Total Subscribers | B4: 2340
A5: Open Rate (30-day avg) | B5: 0.42
A6: Click Rate (30-day avg) | B6: 0.18
A7: New Subs This Month | B7: 187
A8: Unsubscribe Rate | B8: 0.008
A9: Top Topic (by clicks) | B9: PTSD
A12: Monthly Newsletter Performance
A13: Month | B13: Emails Sent | C13: Opens | D13: Open Rate | E13: Clicks | F13: Click Rate | G13: New Subs | H13: Unsubs | I13: Net Growth
A14: Jan 2026 | B14: 1890 | C14: 756 | D14: =C14/B14 -> 0.4 | E14: 302 | F14: =E14/B14 -> 0.15978836 | G14: 210 | H14: 15 | I14: =G14-H14 -> 195
A15: Feb 2026 | B15: 2085 | C15: 876 | D15: =C15/B15 -> 0.42014388 | E15: 397 | F15: =E15/B15 -> 0.19040767 | G15: 225 | H15: 18 | I15: =G15-H15 -> 207
A16: Mar 2026 | B16: 2292 | C16: 985 | D16: =C16/B16 -> 0.42975567 | E16: 436 | F16: =E16/B16 -> 0.19022688 | G16: 240 | H16: 12 | I16: =G16-H16 -> 228
A19: Social Media Performance
A20: Platform | B20: Followers | C20: Posts This Month | D20: Impressions | E20: Engagements | F20: Engagement Rate | G20: Top Post Topic
A21: X / Twitter | B21: 1250 | C21: 62 | D21: 45000 | E21: 3200 | F21: =E21/D21 -> 0.071111111 | G21: Psilocybin PTSD trial
A22: LinkedIn | B22: 890 | C22: 30 | D22: 28000 | E22: 2100 | F22: =E22/D22 -> 0.075 | G22: Depression-inflammation review
A23: Instagram | B23: 2100 | C23: 45 | D23: 67000 | E23: 8500 | F23: =E23/D23 -> 0.12686567 | G23: Gut-brain infographic
A24: TOTAL | B24: =SUM(B21:B23) -> 4240 | C24: =SUM(C21:C23) -> 137 | D24: =SUM(D21:D23) -> 140000 | E24: =SUM(E21:E23) -> 13800 | F24: =IF(D24=0,0,E24/D24) -> 0.098571429

Sheet Budget & Revenue
A1: Budget & Revenue Tracker — Year 1
A3: Monthly Revenue by Source
A4: Revenue Source | B4: Jan | C4: Feb | D4: Mar | E4: Apr | F4: May | G4: Jun | H4: Jul | I4: Aug | J4: Sep | K4: Oct | L4: Nov | M4: Dec | N4: Annual Total
A5: Grants | B5: 0 | C5: 0 | D5: 0 | E5: 0 | F5: 5000 | G5: 5000 | H5: 0 | I5: 0 | J5: 5000 | K5: 5000 | L5: 0 | M5: 5000 | N5: =SUM(B5:M5) -> 25000
A6: Individual Donations | B6: 500 | C6: 500 | D6: 750 | E6: 750 | F6: 1000 | G6: 1000 | H6: 1250 | I6: 1250 | J6: 1500 | K6: 1500 | L6: 2000 | M6: 3000 | N6: =SUM(B6:M6) -> 15000
A7: Research Services | B7: 0 | C7: 0 | D7: 0 | E7: 0 | F7: 0 | G7: 0 | H7: 0 | I7: 0 | J7: 0 | K7: 0 | L7: 0 | M7: 0 | N7: =SUM(B7:M7) -> 0
A8: Subscriptions | B8: 0 | C8: 0 | D8: 0 | E8: 0 | F8: 0 | G8: 0 | H8: 0 | I8: 0 | J8: 0 | K8: 0 | L8: 0 | M8: 0 | N8: =SUM(B8:M8) -> 0
A9: Corporate Sponsorships | B9: 0 | C9: 0 | D9: 0 | E9: 0 | F9: 0 | G9: 0 | H9: 0 | I9: 0 | J9: 0 | K9: 0 | L9: 0 | M9: 0 | N9: =SUM(B9:M9) -> 0
A10: Licensing | B10: 0 | C10: 0 | D10: 0 | E10: 0 | F10: 0 | G10: 0 | H10: 0 | I10: 0 | J10: 0 | K10: 0 | L10: 0 | M10: 0 | N10: =SUM(B10:M10) -> 0
A11: TOTAL REVENUE | B11: =SUM(B5:B10) -> 500 | C11: =SUM(C5:C10) -> 500 | D11: =SUM(D5:D10) -> 750 | E11: =SUM(E5:E10) -> 750 | F11: =SUM(F5:F10) -> 6000 | G11: =SUM(G5:G10) -> 6000 | H11: =SUM(H5:H10) -> 1250 | I11: =SUM(I5:I10) -> 1250 | ... N11: =SUM(N5:N10) -> 40000
A13: Monthly Expenses
A14: Expense Category | B14: Jan | C14: Feb | D14: Mar | E14: Apr | F14: May | G14: Jun | H14: Jul | I14: Aug | J14: Sep | K14: Oct | L14: Nov | M14: Dec | N14: Annual Total
A15: Cloud Hosting (AWS/GCP) | B15: 300 | C15: 300 | D15: 350 | E15: 350 | F15: 400 | G15: 400 | H15: 450 | I15: 450 | J15: 500 | K15: 500 | L15: 500 | M15: 500 | N15: =SUM(B15:M15) -> 5000
A16: AI API Costs (LLM) | B16: 500 | C16: 600 | D16: 700 | E16: 800 | F16: 900 | G16: 1000 | H16: 1000 | I16: 1000 | J16: 1000 | K16: 1000 | L16: 1000 | M16: 1000 | N16: =SUM(B16:M16) -> 10500
A17: Database & Storage | B17: 100 | C17: 100 | D17: 100 | E17: 150 | F17: 150 | G17: 150 | H17: 200 | I17: 200 | J17: 200 | K17: 200 | L17: 200 | M17: 200 | N17: =SUM(B17:M17) -> 1950
A18: Domain & Website | B18: 50 | C18: 20 | D18: 20 | E18: 20 | F18: 20 | G18: 20 | H18: 20 | I18: 20 | J18: 20 | K18: 20 | L18: 20 | M18: 50 | N18: =SUM(B18:M18) -> 300
A19: Email Service (newsletter) | B19: 0 | C19: 30 | D19: 30 | E19: 30 | F19: 30 | G19: 50 | H19: 50 | I19: 50 | J19: 50 | K19: 50 | L19: 50 | M19: 50 | N19: =SUM(B19:M19) -> 470
A20: Legal & Filing Fees | B20: 600 | C20: 0 | D20: 0 | E20: 275 | F20: 0 | G20: 0 | H20: 0 | I20: 0 | J20: 0 | K20: 0 | L20: 0 | M20: 0 | N20: =SUM(B20:M20) -> 875
A21: Insurance | B21: 0 | C21: 0 | D21: 0 | E21: 150 | F21: 150 | G21: 150 | H21: 150 | I21: 150 | J21: 150 | K21: 150 | L21: 150 | M21: 150 | N21: =SUM(B21:M21) -> 1350
A22: Marketing & Social Media | B22: 0 | C22: 50 | D22: 50 | E22: 100 | F22: 100 | G22: 150 | H22: 150 | I22: 200 | J22: 200 | K22: 200 | L22: 250 | M22: 250 | N22: =SUM(B22:M22) -> 1700
A23: Miscellaneous | B23: 100 | C23: 100 | D23: 100 | E23: 100 | F23: 100 | G23: 100 | H23: 100 | I23: 100 | J23: 100 | K23: 100 | L23: 100 | M23: 100 | N23: =SUM(B23:M23) -> 1200
A24: TOTAL EXPENSES | B24: =SUM(B15:B23) -> 1650 | C24: =SUM(C15:C23) -> 1200 | D24: =SUM(D15:D23) -> 1350 | E24: =SUM(E15:E23) -> 1975 | F24: =SUM(F15:F23) -> 1850 | G24: =SUM(G15:G23) -> 2020 | H24: =SUM(H15:H23) -> 2120 | I24: =SUM(I15:I23) -> 2170 | ... N24: =SUM(N15:N23) -> 23345
A25: NET INCOME | B25: =B11-B24 -> -1150 | C25: =C11-C24 -> -700 | D25: =D11-D24 -> -600 | E25: =E11-E24 -> -1225 | F25: =F11-F24 -> 4150 | G25: =G11-G24 -> 3980 | H25: =H11-H24 -> -870 | I25: =I11-I24 -> -920 | ... N25: =N11-N24 -> 16655
A26: CASH BALANCE | B26: =B25 -> -1150 | C26: =B26+C25 -> -1850 | D26: =C26+D25 -> -2450 | E26: =D26+E25 -> -3675 | F26: =E26+F25 -> 475 | G26: =F26+G25 -> 4455 | H26: =G26+H25 -> 3585 | I26: =H26+I25 -> 2665 | J26: =I26+J25 -> 6945 | ... N26: =M26+N25 -> 33310
